<!DOCTYPE PATCH  SYSTEM "http://vvvv.org/versions/vvvv50beta38.1.dtd" >
   <PATCH nodename="C:\Users\kman\Desktop\lightweight_setup\_patches\_graph\gephiVirtualHover.v4p" systemname="gephiVirtualHover" filename="C:\Users\kman\Google Drive\__BAUHAUSORBITS\REALIZATION\02_Person\Kaman\vvvv\190306 vvvv stimulation project\_patches\_graph\gephiVirtualHover.v4p" scrollx="0" scrolly="0">
   <BOUNDS type="Window" left="2436" top="4632" width="16560" height="10620">
   </BOUNDS>
   <PACK Name="dx11" Version="1.3.1">
   </PACK>
   <PACK Name="addonpack" Version="38.1.0">
   </PACK>
   <NODE nodename="IOBox (Node)" componentmode="InABox" id="1">
   <BOUNDS type="Box" left="4020" top="9090" width="795" height="240">
   </BOUNDS>
   <BOUNDS type="Node" left="4020" top="9090" width="0" height="0">
   </BOUNDS>
   <PIN pinname="Descriptive Name" slicecount="1" values="Mouse">
   </PIN>
   <PIN pinname="Input Node" visible="1">
   </PIN>
   </NODE>
   <NODE systemname="Newton (Animation)" nodename="Newton (Animation)" componentmode="Hidden" id="3">
   <BOUNDS type="Node" left="4365" top="5655" width="100" height="100">
   </BOUNDS>
   <PIN pinname="Go To Position" visible="1" slicecount="2" values="0.6277,0.03">
   </PIN>
   <PIN pinname="Position Out" visible="1">
   </PIN>
   <PIN pinname="Acceleration" slicecount="1" values="20">
   </PIN>
   <PIN pinname="Acceleration Out" visible="1">
   </PIN>
   <PIN pinname="Velocity Out" visible="1">
   </PIN>
   </NODE>
   <NODE nodename="IOBox (Value Advanced)" componentmode="InABox" id="2" systemname="IOBox (Value Advanced)">
   <BOUNDS type="Box" left="4755" top="5190" width="420" height="240">
   </BOUNDS>
   <BOUNDS type="Node" left="4755" top="5190" width="0" height="0">
   </BOUNDS>
   <PIN pinname="Y Input Value" slicecount="1" values="10">
   </PIN>
   <PIN pinname="Units" slicecount="1" values="||">
   </PIN>
   <PIN pinname="Precision" slicecount="1" values="4">
   </PIN>
   </NODE>
   <LINK srcnodeid="2" srcpinname="Y Output Value" dstnodeid="3" dstpinname="Acceleration">
   </LINK>
   <NODE systemname="virtualMouseIncrement (Value)" filename="vl\VVVV.Value.virtualMouseIncrement.vl" nodename="virtualMouseIncrement (Value)" componentmode="Hidden" id="21">
   <BOUNDS type="Node" left="2430" top="2700" width="100" height="100">
   </BOUNDS>
   <PIN pinname="Up" visible="1">
   </PIN>
   <PIN pinname="mouseXYXY" visible="1">
   </PIN>
   <BOUNDS type="Box" left="2430" top="2700">
   </BOUNDS>
   <PIN pinname="mouseXYspreadXY" visible="1">
   </PIN>
   <PIN pinname="VectorSpreadInXY" visible="1">
   </PIN>
   </NODE>
   <NODE nodename="IOBox (Value Advanced)" componentmode="InABox" id="22">
   <BOUNDS type="Box" left="7896" top="666" width="480" height="480">
   </BOUNDS>
   <BOUNDS type="Node" left="7896" top="666" width="0" height="0">
   </BOUNDS>
   <PIN pinname="Y Input Value" slicecount="1" visible="1" values="1">
   </PIN>
   <PIN pinname="Units" slicecount="1" values="||">
   </PIN>
   <PIN pinname="Precision" slicecount="1" values="4">
   </PIN>
   <PIN pinname="Value Type" slicecount="1" values="Boolean">
   </PIN>
   <PIN pinname="Behavior" slicecount="1" values="Toggle">
   </PIN>
   <PIN pinname="Descriptive Name" slicecount="1" values="Up(Enabled)">
   </PIN>
   <PIN pinname="Y Output Value" visible="1">
   </PIN>
   </NODE>
   <LINK srcnodeid="22" srcpinname="Y Output Value" dstnodeid="21" dstpinname="Up">
   </LINK>
   <NODE systemname="MouseStates (Mouse Join)" filename="%VVVV%\lib\nodes\plugins\VVVV.Nodes.dll" nodename="MouseStates (Mouse Join)" componentmode="Hidden" id="24">
   <BOUNDS type="Node" left="4020" top="7920" width="100" height="100">
   </BOUNDS>
   <BOUNDS type="Box" left="4020" top="7920">
   </BOUNDS>
   <PIN pinname="PositionXY" visible="1">
   </PIN>
   <PIN pinname="Mouse" visible="1">
   </PIN>
   <PIN pinname="Left Button" visible="1">
   </PIN>
   </NODE>
   <LINK srcnodeid="24" srcpinname="Mouse" dstnodeid="1" dstpinname="Input Node">
   </LINK>
   <NODE nodename="IOBox (Value Advanced)" componentmode="InABox" id="25">
   <BOUNDS type="Box" left="4470" top="7065" width="480" height="480">
   </BOUNDS>
   <BOUNDS type="Node" left="4470" top="7065" width="0" height="0">
   </BOUNDS>
   <PIN pinname="Y Input Value" slicecount="1" visible="1" values="0">
   </PIN>
   <PIN pinname="Units" slicecount="1" values="||">
   </PIN>
   <PIN pinname="Precision" slicecount="1" values="4">
   </PIN>
   <PIN pinname="Value Type" slicecount="1" values="Boolean">
   </PIN>
   <PIN pinname="Behavior" slicecount="1" values="Toggle">
   </PIN>
   <PIN pinname="X Input Value" slicecount="1" values="0">
   </PIN>
   </NODE>
   <LINK srcnodeid="25" srcpinname="Y Output Value" dstnodeid="24" dstpinname="Left Button">
   </LINK>
   <NODE nodename="IOBox (Color)" componentmode="InABox" id="29" systemname="IOBox (Color)">
   <BOUNDS type="Box" left="9600" top="6945" width="660" height="240">
   </BOUNDS>
   <BOUNDS type="Node" left="9600" top="6945" width="0" height="0">
   </BOUNDS>
   <PIN pinname="Color Input" slicecount="1" visible="1" values="|1.00000,0.20657,0.00000,1.00000|">
   </PIN>
   <PIN pinname="Color Output" visible="1">
   </PIN>
   </NODE>
   <NODE systemname="IOBox (Value Advanced)" nodename="IOBox (Value Advanced)" componentmode="InABox" id="26">
   <BOUNDS type="Node" left="8820" top="6075" width="100" height="100">
   </BOUNDS>
   <BOUNDS type="Box" left="8820" top="6075" width="525" height="510">
   </BOUNDS>
   <PIN pinname="Y Output Value" visible="1">
   </PIN>
   <PIN pinname="Y Input Value" slicecount="2" values="0.02,0.02">
   </PIN>
   <PIN pinname="Rows" slicecount="1" values="2">
   </PIN>
   <PIN pinname="SliceCount Mode" slicecount="1" values="ColsRowsPages">
   </PIN>
   </NODE>
   <NODE systemname="Quad (DX11.Layer)" nodename="Quad (DX11.Layer)" componentmode="Hidden" id="28" filename="%VVVV%\packs\dx11\nodes\plugins\base\VVVV.DX11.Nodes.dll">
   <BOUNDS type="Node" left="8430" top="7440" width="100" height="100">
   </BOUNDS>
   <PIN pinname="Transform" visible="1" slicecount="1" values="||">
   </PIN>
   <PIN pinname="Layer" visible="1">
   </PIN>
   <PIN pinname="Color" visible="1">
   </PIN>
   <BOUNDS type="Box" left="8430" top="7440">
   </BOUNDS>
   <PIN pinname="Render State" visible="1" slicecount="1" values="||">
   </PIN>
   </NODE>
   <LINK srcnodeid="29" srcpinname="Color Output" dstnodeid="28" dstpinname="Color">
   </LINK>
   <NODE nodename="IOBox (Node)" componentmode="InABox" id="30">
   <BOUNDS type="Box" left="8430" top="9090" width="795" height="240">
   </BOUNDS>
   <BOUNDS type="Node" left="8430" top="9090" width="0" height="0">
   </BOUNDS>
   <PIN pinname="Descriptive Name" slicecount="1" values="|mouse debug|">
   </PIN>
   <PIN pinname="Input Node" visible="1">
   </PIN>
   </NODE>
   <NODE nodename="IOBox (Value Advanced)" componentmode="InABox" id="31">
   <BOUNDS type="Box" left="1320" top="7770" width="795" height="480">
   </BOUNDS>
   <BOUNDS type="Node" left="1320" top="7770" width="0" height="0">
   </BOUNDS>
   <PIN pinname="Units" slicecount="1" values="||">
   </PIN>
   <PIN pinname="Precision" slicecount="1" values="4">
   </PIN>
   <PIN pinname="Vector Size" slicecount="1" values="2">
   </PIN>
   <PIN pinname="Rows" slicecount="1" values="2">
   </PIN>
   <PIN pinname="Descriptive Name" slicecount="1" values="mouseXYXY">
   </PIN>
   <PIN pinname="Y Input Value" visible="1">
   </PIN>
   </NODE>
   <NODE nodename="IOBox (Value Advanced)" componentmode="InABox" id="62" systemname="IOBox (Value Advanced)">
   <BOUNDS type="Box" left="3405" top="870" width="765" height="480">
   </BOUNDS>
   <BOUNDS type="Node" left="3405" top="870" width="0" height="0">
   </BOUNDS>
   <PIN pinname="Y Input Value" slicecount="2" visible="1" values="200,200">
   </PIN>
   <PIN pinname="Units" slicecount="1" values="||">
   </PIN>
   <PIN pinname="Precision" slicecount="1" values="4">
   </PIN>
   <PIN pinname="Value Type" slicecount="1" values="Integer">
   </PIN>
   <PIN pinname="Vector Size" slicecount="1" values="2">
   </PIN>
   <PIN pinname="Rows" slicecount="1" values="2">
   </PIN>
   <PIN pinname="Y Output Value" visible="1">
   </PIN>
   </NODE>
   <NODE nodename="GridSpread (Spreads 2d)" componentmode="Hidden" id="61" systemname="GridSpread (Spreads 2d)" filename="%VVVV%\lib\nodes\modules\2D\GridSpread (Spreads 2d).v4p">
   <BOUNDS type="Node" left="480" top="1755" width="2610" height="270">
   </BOUNDS>
   <BOUNDS type="Box" left="480" top="1755" width="0" height="0">
   </BOUNDS>
   <BOUNDS type="Window" left="8265" top="4125" width="8205" height="8700">
   </BOUNDS>
   <PIN pinname="Centered" slicecount="1" visible="1" values="1">
   </PIN>
   <PIN pinname="Row Major" visible="1">
   </PIN>
   <PIN pinname="SizeXY" visible="1">
   </PIN>
   <PIN pinname="CenterXY" visible="1">
   </PIN>
   <PIN pinname="XY" visible="1">
   </PIN>
   <PIN pinname="ResolutionXY" visible="1">
   </PIN>
   </NODE>
   <NODE nodename="IOBox (Value Advanced)" componentmode="InABox" id="60" systemname="IOBox (Value Advanced)">
   <BOUNDS type="Box" left="1740" top="870" width="480" height="480">
   </BOUNDS>
   <BOUNDS type="Node" left="1740" top="870" width="0" height="0">
   </BOUNDS>
   <PIN pinname="Y Input Value" slicecount="1" visible="1" values="1">
   </PIN>
   <PIN pinname="Units" slicecount="1" values="||">
   </PIN>
   <PIN pinname="Precision" slicecount="1" values="4">
   </PIN>
   <PIN pinname="Value Type" slicecount="1" values="Boolean">
   </PIN>
   <PIN pinname="Behavior" slicecount="1" values="Toggle">
   </PIN>
   <PIN pinname="X Input Value" slicecount="1" values="1">
   </PIN>
   </NODE>
   <LINK srcnodeid="60" srcpinname="Y Output Value" dstnodeid="61" dstpinname="Centered">
   </LINK>
   <NODE nodename="IOBox (String)" componentmode="InABox" id="59" systemname="IOBox (String)">
   <BOUNDS type="Node" left="3345" top="555" width="420" height="270">
   </BOUNDS>
   <BOUNDS type="Box" left="3345" top="555" width="855" height="240">
   </BOUNDS>
   <PIN pinname="Input String" visible="0" slicecount="1" values="Resolution">
   </PIN>
   <PIN pinname="Output String" visible="0">
   </PIN>
   <PIN pinname="Show Grid" slicecount="1" values="0">
   </PIN>
   <PIN pinname="String Type" slicecount="1" values="MultiLine">
   </PIN>
   </NODE>
   <NODE nodename="IOBox (String)" componentmode="InABox" id="58" systemname="IOBox (String)">
   <BOUNDS type="Node" left="1695" top="555" width="420" height="270">
   </BOUNDS>
   <BOUNDS type="Box" left="1695" top="555" width="810" height="285">
   </BOUNDS>
   <PIN pinname="Input String" visible="0" slicecount="1" values="Centered">
   </PIN>
   <PIN pinname="Output String" visible="0">
   </PIN>
   <PIN pinname="Show Grid" slicecount="1" values="0">
   </PIN>
   <PIN pinname="String Type" slicecount="1" values="MultiLine">
   </PIN>
   </NODE>
   <NODE nodename="IOBox (Value Advanced)" componentmode="InABox" id="57" systemname="IOBox (Value Advanced)">
   <BOUNDS type="Box" left="2550" top="870" width="480" height="480">
   </BOUNDS>
   <BOUNDS type="Node" left="2550" top="870" width="0" height="0">
   </BOUNDS>
   <PIN pinname="Y Input Value" slicecount="1" visible="1" values="0">
   </PIN>
   <PIN pinname="Units" slicecount="1" values="||">
   </PIN>
   <PIN pinname="Precision" slicecount="1" values="4">
   </PIN>
   <PIN pinname="Value Type" slicecount="1" values="Boolean">
   </PIN>
   <PIN pinname="Behavior" slicecount="1" values="Toggle">
   </PIN>
   <PIN pinname="X Input Value" slicecount="1" values="0">
   </PIN>
   </NODE>
   <LINK srcnodeid="57" srcpinname="Y Output Value" dstnodeid="61" dstpinname="Row Major">
   </LINK>
   <NODE nodename="IOBox (String)" componentmode="InABox" id="56" systemname="IOBox (String)">
   <BOUNDS type="Node" left="2505" top="555" width="420" height="270">
   </BOUNDS>
   <BOUNDS type="Box" left="2505" top="555" width="810" height="285">
   </BOUNDS>
   <PIN pinname="Input String" visible="0" slicecount="1" values="|Row Major|">
   </PIN>
   <PIN pinname="Output String" visible="0">
   </PIN>
   <PIN pinname="Show Grid" slicecount="1" values="0">
   </PIN>
   <PIN pinname="String Type" slicecount="1" values="MultiLine">
   </PIN>
   </NODE>
   <NODE nodename="IOBox (Value Advanced)" componentmode="InABox" id="55" systemname="IOBox (Value Advanced)">
   <BOUNDS type="Box" left="1125" top="870" width="465" height="570">
   </BOUNDS>
   <BOUNDS type="Node" left="1125" top="870" width="0" height="0">
   </BOUNDS>
   <PIN pinname="Y Input Value" slicecount="2" visible="1" values="1.5,0.9">
   </PIN>
   <PIN pinname="Units" slicecount="1" values="||">
   </PIN>
   <PIN pinname="Precision" slicecount="1" values="4">
   </PIN>
   <PIN pinname="Vector Size" slicecount="1" values="2">
   </PIN>
   <PIN pinname="Rows" slicecount="1" values="2">
   </PIN>
   </NODE>
   <LINK srcnodeid="55" srcpinname="Y Output Value" dstnodeid="61" dstpinname="SizeXY">
   </LINK>
   <NODE nodename="IOBox (String)" componentmode="InABox" id="54" systemname="IOBox (String)">
   <BOUNDS type="Node" left="1080" top="555" width="420" height="270">
   </BOUNDS>
   <BOUNDS type="Box" left="1080" top="555" width="495" height="240">
   </BOUNDS>
   <PIN pinname="Input String" visible="0" slicecount="1" values="Size">
   </PIN>
   <PIN pinname="Output String" visible="0">
   </PIN>
   <PIN pinname="Show Grid" slicecount="1" values="0">
   </PIN>
   <PIN pinname="String Type" slicecount="1" values="MultiLine">
   </PIN>
   </NODE>
   <NODE nodename="IOBox (Value Advanced)" componentmode="InABox" id="53" systemname="IOBox (Value Advanced)">
   <BOUNDS type="Box" left="195" top="870" width="540" height="555">
   </BOUNDS>
   <BOUNDS type="Node" left="195" top="870" width="0" height="0">
   </BOUNDS>
   <PIN pinname="Y Input Value" slicecount="2" visible="1" values="0,0">
   </PIN>
   <PIN pinname="Units" slicecount="1" values="||">
   </PIN>
   <PIN pinname="Precision" slicecount="1" values="4">
   </PIN>
   <PIN pinname="Vector Size" slicecount="1" values="2">
   </PIN>
   <PIN pinname="Rows" slicecount="1" values="2">
   </PIN>
   </NODE>
   <LINK srcnodeid="53" srcpinname="Y Output Value" dstnodeid="61" dstpinname="CenterXY">
   </LINK>
   <NODE nodename="IOBox (String)" componentmode="InABox" id="52" systemname="IOBox (String)">
   <BOUNDS type="Node" left="135" top="570" width="420" height="270">
   </BOUNDS>
   <BOUNDS type="Box" left="135" top="570" width="735" height="240">
   </BOUNDS>
   <PIN pinname="Input String" visible="0" slicecount="1" values="CenterXY">
   </PIN>
   <PIN pinname="Output String" visible="0">
   </PIN>
   <PIN pinname="Show Grid" slicecount="1" values="0">
   </PIN>
   <PIN pinname="String Type" slicecount="1" values="MultiLine">
   </PIN>
   </NODE>
   <NODE systemname="GetSlice (Spreads)" nodename="GetSlice (Spreads)" componentmode="Hidden" id="63">
   <BOUNDS type="Node" left="765" top="2745" width="100" height="100">
   </BOUNDS>
   <PIN pinname="Input" visible="1">
   </PIN>
   <PIN pinname="Output" visible="1">
   </PIN>
   <PIN pinname="Index" visible="1">
   </PIN>
   <PIN pinname="Bin Size" slicecount="1" values="2">
   </PIN>
   </NODE>
   <LINK srcnodeid="61" srcpinname="XY" dstnodeid="63" dstpinname="Input">
   </LINK>
   <NODE nodename="IOBox (Value Advanced)" componentmode="InABox" id="64">
   <BOUNDS type="Box" left="1485" top="2370" width="795" height="240">
   </BOUNDS>
   <BOUNDS type="Node" left="1485" top="2370" width="0" height="0">
   </BOUNDS>
   <PIN pinname="Y Input Value" slicecount="1" visible="1" values="45">
   </PIN>
   <PIN pinname="Units" slicecount="1" values="||">
   </PIN>
   <PIN pinname="Precision" slicecount="1" values="4">
   </PIN>
   <PIN pinname="Value Type" slicecount="1" values="Integer">
   </PIN>
   </NODE>
   <LINK srcnodeid="64" srcpinname="Y Output Value" dstnodeid="63" dstpinname="Index">
   </LINK>
   <LINK srcnodeid="61" srcpinname="XY" dstnodeid="21" dstpinname="VectorSpreadInXY">
   </LINK>
   <NODE systemname="Transform (Transform 2d Vector)" nodename="Transform (Transform 2d Vector)" componentmode="Hidden" id="67">
   <BOUNDS type="Node" left="8430" top="6900" width="100" height="100">
   </BOUNDS>
   <PIN pinname="TranslateXY" visible="1">
   </PIN>
   </NODE>
   <LINK srcnodeid="26" srcpinname="Y Output Value" dstnodeid="67" dstpinname="ScaleXY">
   </LINK>
   <LINK srcnodeid="67" srcpinname="Transform Out" dstnodeid="28" dstpinname="Transform">
   </LINK>
   <NODE id="34" nodename="IOBox (Value Advanced)" componentmode="InABox" systemname="IOBox (Value Advanced)">
   <PIN pinname="Y Input Value" slicecount="2" values="0.6277,0.03">
   </PIN>
   <PIN pinname="X Input Value" slicecount="2" values="0,0">
   </PIN>
   <PIN pinname="Vector Size" slicecount="1" values="2">
   </PIN>
   <PIN pinname="Rows" slicecount="1" values="2">
   </PIN>
   <BOUNDS type="Box" left="5760" top="615" width="870" height="630">
   </BOUNDS>
   <BOUNDS type="Node" left="5760" top="615" width="0" height="0">
   </BOUNDS>
   <PIN pinname="Show Slider" slicecount="1" values="0">
   </PIN>
   <PIN pinname="Show Grid" slicecount="1" values="1">
   </PIN>
   <PIN pinname="Precision" slicecount="1" values="4">
   </PIN>
   <PIN pinname="Y Output Value" visible="1">
   </PIN>
   <PIN pinname="Units" slicecount="1" values="||">
   </PIN>
   <PIN pinname="Descriptive Name" slicecount="1" values="|hardcoded value|">
   </PIN>
   </NODE>
   <NODE systemname="Blend (DX11.RenderState)" filename="%VVVV%\packs\dx11\nodes\plugins\base\VVVV.DX11.Nodes.dll" nodename="Blend (DX11.RenderState)" componentmode="Hidden" id="68">
   <BOUNDS type="Node" left="7740" top="7065" width="100" height="100">
   </BOUNDS>
   <BOUNDS type="Box" left="7740" top="7065" width="3000" height="3000">
   </BOUNDS>
   <PIN pinname="Render State" visible="1" slicecount="1" values="||">
   </PIN>
   <PIN pinname="Mode" slicecount="1" values="Blend">
   </PIN>
   </NODE>
   <NODE systemname="SetAlpha (Color)" nodename="SetAlpha (Color)" componentmode="Hidden" id="69">
   <BOUNDS type="Node" left="9645" top="6450" width="100" height="100">
   </BOUNDS>
   <PIN pinname="Output" visible="1">
   </PIN>
   <PIN pinname="Alpha" slicecount="1" visible="1" values="0.6">
   </PIN>
   <PIN pinname="Input" slicecount="1" values="|1.00000,1.00000,1.00000,1.00000|">
   </PIN>
   </NODE>
   <LINK srcnodeid="69" srcpinname="Output" dstnodeid="29" dstpinname="Color Input">
   </LINK>
   <NODE nodename="IOBox (Value Advanced)" componentmode="InABox" id="70">
   <BOUNDS type="Box" left="4380" top="3405" width="795" height="480">
   </BOUNDS>
   <BOUNDS type="Node" left="4380" top="3405" width="0" height="0">
   </BOUNDS>
   <PIN pinname="Units" slicecount="1" values="||">
   </PIN>
   <PIN pinname="Precision" slicecount="1" values="4">
   </PIN>
   <PIN pinname="Vector Size" slicecount="1" values="2">
   </PIN>
   <PIN pinname="Rows" slicecount="1" values="2">
   </PIN>
   <PIN pinname="Y Output Value" visible="1">
   </PIN>
   <PIN pinname="Y Input Value" visible="1">
   </PIN>
   </NODE>
   <NODE systemname="RenderState (DX11)" filename="%VVVV%\packs\dx11\nodes\plugins\base\VVVV.DX11.Nodes.dll" nodename="RenderState (DX11)" componentmode="Hidden" id="73">
   <BOUNDS type="Node" left="6705" top="7065" width="100" height="100">
   </BOUNDS>
   <BOUNDS type="Box" left="6705" top="7065" width="3000" height="3000">
   </BOUNDS>
   <PIN pinname="Render State" visible="1">
   </PIN>
   <PIN pinname="Rasterizer Mode" slicecount="1" values="NoCullWireframe">
   </PIN>
   </NODE>
   <LINK srcnodeid="21" srcpinname="mouseXYXY" dstnodeid="70" dstpinname="Y Input Value">
   </LINK>
   <LINK srcnodeid="68" srcpinname="Render State" dstnodeid="28" dstpinname="Render State">
   </LINK>
   <LINK srcnodeid="3" srcpinname="Position Out" dstnodeid="67" dstpinname="TranslateXY">
   </LINK>
   <LINK srcnodeid="3" srcpinname="Position Out" dstnodeid="24" dstpinname="PositionXY">
   </LINK>
   <LINK srcnodeid="3" srcpinname="Position Out" dstnodeid="31" dstpinname="Y Input Value">
   </LINK>
   <NODE systemname="Group (DX11.Layer)" filename="%VVVV%\packs\dx11\nodes\plugins\base\VVVV.DX11.Nodes.dll" nodename="Group (DX11.Layer)" componentmode="Hidden" id="80">
   <BOUNDS type="Node" left="8415" top="8220" width="100" height="100">
   </BOUNDS>
   <BOUNDS type="Box" left="8415" top="8220" width="3000" height="3000">
   </BOUNDS>
   <PIN pinname="Layer 1" visible="1">
   </PIN>
   <PIN pinname="Layer 2" visible="1" slicecount="1" values="||">
   </PIN>
   <PIN pinname="Layer Out" visible="1">
   </PIN>
   </NODE>
   <LINK srcnodeid="28" srcpinname="Layer" dstnodeid="80" dstpinname="Layer 1">
   </LINK>
   <LINK srcnodeid="80" srcpinname="Layer Out" dstnodeid="30" dstpinname="Input Node">
   </LINK>
   <NODE systemname="Switch (Value Input)" nodename="Switch (Value Input)" componentmode="Hidden" id="89">
   <BOUNDS type="Node" left="4005" top="4575" width="100" height="100">
   </BOUNDS>
   <PIN pinname="Input 1" visible="1">
   </PIN>
   <PIN pinname="Input 2" visible="1">
   </PIN>
   <PIN pinname="Switch" visible="1">
   </PIN>
   <PIN pinname="Output" visible="1">
   </PIN>
   </NODE>
   <LINK srcnodeid="70" srcpinname="Y Output Value" dstnodeid="89" dstpinname="Input 1">
   </LINK>
   <LINK srcnodeid="34" srcpinname="Y Output Value" dstnodeid="89" dstpinname="Input 2">
   </LINK>
   <NODE nodename="IOBox (Value Advanced)" componentmode="InABox" id="90">
   <BOUNDS type="Box" left="4710" top="600" width="480" height="480">
   </BOUNDS>
   <BOUNDS type="Node" left="4710" top="600" width="0" height="0">
   </BOUNDS>
   <PIN pinname="Y Input Value" slicecount="1" visible="1" values="0">
   </PIN>
   <PIN pinname="Units" slicecount="1" values="||">
   </PIN>
   <PIN pinname="Precision" slicecount="1" values="4">
   </PIN>
   <PIN pinname="Value Type" slicecount="1" values="Boolean">
   </PIN>
   <PIN pinname="Behavior" slicecount="1" values="Toggle">
   </PIN>
   <PIN pinname="Descriptive Name" slicecount="1" values="HoverSwitch">
   </PIN>
   </NODE>
   <LINK srcnodeid="90" srcpinname="Y Output Value" dstnodeid="89" dstpinname="Switch">
   </LINK>
   <LINK srcnodeid="89" srcpinname="Output" dstnodeid="3" dstpinname="Go To Position">
   </LINK>
   <PACK Name="dx11.particles" Version="1.0.6">
   </PACK>
   <PACK Name="vvvv-Message" Version="2.9.10">
   </PACK>
   <NODE systemname="Switch (Value Input)" nodename="Switch (Value Input)" componentmode="Hidden" id="92">
   <BOUNDS type="Node" left="3648" top="1524" width="100" height="100">
   </BOUNDS>
   <PIN pinname="Input 2" visible="1">
   </PIN>
   <PIN pinname="Switch" visible="1">
   </PIN>
   <PIN pinname="Output" visible="1">
   </PIN>
   </NODE>
   <LINK srcnodeid="62" srcpinname="Y Output Value" dstnodeid="92" dstpinname="Input 2">
   </LINK>
   <LINK srcnodeid="22" srcpinname="Y Output Value" dstnodeid="92" dstpinname="Switch">
   </LINK>
   <LINK srcnodeid="92" srcpinname="Output" dstnodeid="61" dstpinname="ResolutionXY">
   </LINK>
   <NODE nodename="IOBox (String)" systemname="IOBox (String)" componentmode="InABox" id="93">
   <BOUNDS type="Node" left="4284" top="1512" width="588" height="240">
   </BOUNDS>
   <BOUNDS type="Box" left="4284" top="1512" width="588" height="240">
   </BOUNDS>
   <PIN pinname="Input String" visible="0" slicecount="1" values="!Edited">
   </PIN>
   <PIN pinname="Output String" visible="0">
   </PIN>
   <PIN pinname="Show Grid" slicecount="1" values="0">
   </PIN>
   <PIN pinname="String Type" slicecount="1" values="MultiLine">
   </PIN>
   </NODE>
   </PATCH>